pkgexampleconcurrency/__init__.py
pkgexampleconcurrency/my_concurrency_module.py
pkgexampleconcurrency/myasyncio.py
pkgexampleconcurrency/myconcurrentfutures.py
pkgexampleconcurrency/mymultiprocessing.py
pkgexampleconcurrency/mythreading.py
pkgexampleconcurrency-0.0.9.dist-info/LICENCE
pkgexampleconcurrency-0.0.9.dist-info/METADATA
pkgexampleconcurrency-0.0.9.dist-info/WHEEL
pkgexampleconcurrency-0.0.9.dist-info/entry_points.txt
pkgexampleconcurrency-0.0.9.dist-info/top_level.txt
pkgexampleconcurrency-0.0.9.dist-info/RECORD
