Metadata-Version: 2.1
Name: pkgexampleconcurrency
Version: 0.0.9
Summary: A simple concurrency package example
Author-email: Good Boy <pythonic@rexbytes.com>
Project-URL: Homepage, https://github.com/RexBytes/pkgexampleconcurrency
Project-URL: Bug Tracker, https://github.com/RexBytes/pkgexampleconcurrency/issues
Project-URL: Download URL, https://github.com/RexBytes/pkgexampleconcurrency/archive/refs/tags/v0.0.9.tar.gz
Classifier: Programming Language :: Python :: 3
Classifier: License :: OSI Approved :: MIT License
Classifier: Operating System :: OS Independent
Requires-Python: >=3.7
License-File: LICENCE
